omnicrawls/__init__.py
omnicrawls/github_crawler.py
omnicrawls/linkedin_crawler.py
omnicrawls/website_crawler.py
omnicrawls-2.1.dist-info/LICENSE
omnicrawls-2.1.dist-info/METADATA
omnicrawls-2.1.dist-info/WHEEL
omnicrawls-2.1.dist-info/top_level.txt
omnicrawls-2.1.dist-info/RECORD
