Metadata-Version: 2.1
Name: omnicrawls
Version: 2.1
Summary: A Python library for crawling LinkedIn data and GitHub repos and scrap websites.
Author: Vinayak Pratap Rana
Author-email: perrcroshado@gmail.com
Classifier: Programming Language :: Python :: 3
Classifier: License :: OSI Approved :: MIT License
Classifier: Operating System :: OS Independent
Requires-Python: >=3.6
License-File: LICENSE
Requires-Dist: requests
Requires-Dist: bs4
Requires-Dist: selenium
Requires-Dist: webdriver-manager
Requires-Dist: python-dotenv
